strukturen/__init__.py
strukturen/geometry.py
strukturen-0.1.0.dist-info/LICENSE
strukturen-0.1.0.dist-info/METADATA
strukturen-0.1.0.dist-info/WHEEL
strukturen-0.1.0.dist-info/top_level.txt
strukturen-0.1.0.dist-info/RECORD
