Metadata-Version: 2.1
Name: strukturen
Version: 0.1.0
Summary: Implementation of various data structures
Home-page: https://github.com/pedroteosousa/python-structures
Author: Pedro Sousa
Author-email: pedroteosousa@gmail.com
License: UNKNOWN
Platform: UNKNOWN
Classifier: Programming Language :: Python :: 3
